ooze/__init__.py
ooze/pool.py
ooze-1.0.1.dist-info/LICENSE
ooze-1.0.1.dist-info/METADATA
ooze-1.0.1.dist-info/WHEEL
ooze-1.0.1.dist-info/top_level.txt
ooze-1.0.1.dist-info/RECORD
