Metadata-Version: 2.1
Name: ooze
Version: 1.0.1
Summary: Brain-dead simple dependency injection
Author-email: Steve Brettschneider <steve@bluehousefamily.com>
License: GNU AFFERO GENERAL PUBLIC LICENSE
Project-URL: Homepage, https://github.com/brettschneider/ooze
Project-URL: Bug Tracker, https://github.com/brettschneider/ooze/issues
Project-URL: Documentation, https://ooze.readthedocs.io/en/latest/
Classifier: Programming Language :: Python :: 3.9
Classifier: Programming Language :: Python :: 3.10
Classifier: Programming Language :: Python :: 3.11
Classifier: Programming Language :: Python :: 3.12
Classifier: License :: OSI Approved :: GNU General Public License v3 or later (GPLv3+)
Classifier: Operating System :: OS Independent
Classifier: Framework :: Bottle
Classifier: Framework :: FastAPI
Classifier: Framework :: Flask
Requires-Python: >=3.9
License-File: LICENSE
Requires-Dist: pyyaml
